[
    {
      "id": "633a456eb4c308e1df64da39",
      "price": 437,
      "name": "Hurst Santiago"
    },
    {
      "id": "633a456e485bd7ab147b51e5",
      "price": 572,
      "name": "Williams Hickman"
    },
    {
      "id": "633a456e812186a8e63cbe26",
      "price": 515,
      "name": "Lewis Cain"
    },
    {
      "id": "633a456edf6607f5227cb644",
      "price": 238,
      "name": "Gill Crawford"
    },
    {
      "id": "633a456e52fad800b6689ee2",
      "price": 587,
      "name": "Beverly Oconnor"
    }
  ]